vangja/__init__.py
vangja/time_series.py
vangja/components/__init__.py
vangja/components/beta_constant.py
vangja/components/fourier_seasonality.py
vangja/components/linear_trend.py
vangja/components/normal_constant.py
vangja/components/uniform_constant.py
vangja-0.1.3.dist-info/LICENSE
vangja-0.1.3.dist-info/METADATA
vangja-0.1.3.dist-info/WHEEL
vangja-0.1.3.dist-info/top_level.txt
vangja-0.1.3.dist-info/RECORD
