Metadata-Version: 2.2
Name: vangja
Version: 0.1.3
Summary: A time-series forecasting package with an intuitive API capable of modeling short time series with prior knowledge derived from a similar long time series.
Author-email: Jovan Krajevski <jovan.krajevski@gmail.com>
Project-URL: Repository, https://github.com/jovan-krajevski/vangja
Classifier: Programming Language :: Python :: 3
Classifier: License :: OSI Approved :: MIT License
Requires-Python: <3.14,>=3.12
License-File: LICENSE
Requires-Dist: scikit-learn~=1.6.1
Requires-Dist: pymc-extras==0.2.3
Requires-Dist: blackjax==1.2.4
